blinkcomputing/__init__.py
blinkcomputing-0.0.5.dist-info/METADATA
blinkcomputing-0.0.5.dist-info/RECORD
blinkcomputing-0.0.5.dist-info/WHEEL
blinkcomputing-0.0.5.dist-info/top_level.txt
