Metadata-Version: 2.1
Name: blinkcomputing
Version: 0.0.5
Summary: Client for Blink Computing service
Home-page: https://github.com/blinkcomputing/blink-client
Maintainer: Blink Computing
Maintainer-email: info@blinkcomputing.co
License: Apache License, Version 2.0
Platform: UNKNOWN
Requires-Dist: requests
